README.md
setup.cfg
setup.py
comovotadeputado/__init__.py
comovotadeputado.egg-info/PKG-INFO
comovotadeputado.egg-info/SOURCES.txt
comovotadeputado.egg-info/dependency_links.txt
comovotadeputado.egg-info/not-zip-safe
comovotadeputado.egg-info/requires.txt
comovotadeputado.egg-info/top_level.txt
comovotadeputado/cache/__init__.py
comovotadeputado/cache/constants.py
comovotadeputado/constants/__init__.py
comovotadeputado/constants/http.py
comovotadeputado/controllers/__init__.py
comovotadeputado/controllers/attendances.py
comovotadeputado/controllers/votes.py
comovotadeputado/errors/__init__.py
comovotadeputado/errors/messages.py
comovotadeputado/models/__init__.py
comovotadeputado/models/proposition.py
comovotadeputado/opendata/__init__.py
comovotadeputado/opendata/attendance_values.py
comovotadeputado/opendata/constants.py
comovotadeputado/opendata/controller.py
comovotadeputado/utils/__init__.py
comovotadeputado/utils/parser.py
tests/__init__.py
tests/opendata/__init__.py
tests/opendata/test_controller.py