Metadata-Version: 1.1
Name: comovotadeputado
Version: 1.0
Summary: To describe
Home-page: https://github.com/italo-batista/como-vota-deputado
Author: Italo Batista
Author-email: italohmb@gmail.com
License: UNKNOWN
Download-URL: https://github.com/italo-batista/como-vota-deputado/archive/1.0.tar.gz
Keywords: opendata,politicians,br
Platform: UNKNOWN
